{"note":"This file is an internal implementation detail to speed up HTML report generation. Its format can change at any time. You might be looking for the JSON report: https://coverage.rtfd.io/cmd.html#cmd-json","format":5,"version":"7.11.2","globals":"6b2ce021f719a3dce8ea4a1f6db88bc4","files":{"z_48a8711fda13fe93___init___py":{"hash":"d9368f1ff0662fcba871868a500ae558","index":{"url":"z_48a8711fda13fe93___init___py.html","file":"filterweb/__init__.py","description":"","nums":{"precision":0,"n_files":1,"n_statements":5,"n_excluded":0,"n_missing":0,"n_branches":0,"n_partial_branches":0,"n_missing_branches":0}}},"z_48a8711fda13fe93__cli_py":{"hash":"8599b47c0381d9808ba0f7723a744b6f","index":{"url":"z_48a8711fda13fe93__cli_py.html","file":"filterweb/_cli.py","description":"","nums":{"precision":0,"n_files":1,"n_statements":73,"n_excluded":0,"n_missing":18,"n_branches":8,"n_partial_branches":3,"n_missing_branches":3}}},"z_48a8711fda13fe93__version_py":{"hash":"2f7bf8a01eb15f0ff444d900b2a9f7cb","index":{"url":"z_48a8711fda13fe93__version_py.html","file":"filterweb/_version.py","description":"","nums":{"precision":0,"n_files":1,"n_statements":1,"n_excluded":0,"n_missing":0,"n_branches":0,"n_partial_branches":0,"n_missing_branches":0}}},"z_48a8711fda13fe93_base_py":{"hash":"5e400996f723b9119d9ededa06087325","index":{"url":"z_48a8711fda13fe93_base_py.html","file":"filterweb/base.py","description":"","nums":{"precision":0,"n_files":1,"n_statements":11,"n_excluded":0,"n_missing":1,"n_branches":2,"n_partial_branches":1,"n_missing_branches":1}}},"z_5d635af15a96163f___init___py":{"hash":"13f4de3b46c0544c7d8c468f0943e216","index":{"url":"z_5d635af15a96163f___init___py.html","file":"filterweb/filter/__init__.py","description":"","nums":{"precision":0,"n_files":1,"n_statements":7,"n_excluded":0,"n_missing":2,"n_branches":0,"n_partial_branches":0,"n_missing_branches":0}}},"z_5d635af15a96163f_filter_py":{"hash":"3311f3f380f1554a1cb99cf23998741d","index":{"url":"z_5d635af15a96163f_filter_py.html","file":"filterweb/filter/filter.py","description":"","nums":{"precision":0,"n_files":1,"n_statements":6,"n_excluded":0,"n_missing":1,"n_branches":0,"n_partial_branches":0,"n_missing_branches":0}}},"z_5d635af15a96163f_jinja_py":{"hash":"a82eb842c5e66e4e98a17bc9d42ef2bd","index":{"url":"z_5d635af15a96163f_jinja_py.html","file":"filterweb/filter/jinja.py","description":"","nums":{"precision":0,"n_files":1,"n_statements":41,"n_excluded":0,"n_missing":6,"n_branches":12,"n_partial_branches":2,"n_missing_branches":4}}},"z_5d635af15a96163f_process_py":{"hash":"27a42bf6124fa00ed38b314230c7220e","index":{"url":"z_5d635af15a96163f_process_py.html","file":"filterweb/filter/process.py","description":"","nums":{"precision":0,"n_files":1,"n_statements":21,"n_excluded":0,"n_missing":7,"n_branches":4,"n_partial_branches":0,"n_missing_branches":4}}},"z_5d635af15a96163f_pygments_py":{"hash":"13c3dd0e2c9f521c9eb191cd73b6f8d2","index":{"url":"z_5d635af15a96163f_pygments_py.html","file":"filterweb/filter/pygments.py","description":"","nums":{"precision":0,"n_files":1,"n_statements":24,"n_excluded":0,"n_missing":0,"n_branches":4,"n_partial_branches":0,"n_missing_branches":0}}},"z_48a8711fda13fe93_index_py":{"hash":"70bd5e68c1cf11acc4d5b503fd8ee2cd","index":{"url":"z_48a8711fda13fe93_index_py.html","file":"filterweb/index.py","description":"","nums":{"precision":0,"n_files":1,"n_statements":31,"n_excluded":0,"n_missing":0,"n_branches":10,"n_partial_branches":0,"n_missing_branches":0}}},"z_c22ab56dc5cc35f0___init___py":{"hash":"72c0fdfc071f729336b4764bde28b0c7","index":{"url":"z_c22ab56dc5cc35f0___init___py.html","file":"filterweb/input/__init__.py","description":"","nums":{"precision":0,"n_files":1,"n_statements":23,"n_excluded":0,"n_missing":6,"n_branches":0,"n_partial_branches":0,"n_missing_branches":0}}},"z_c22ab56dc5cc35f0_file_py":{"hash":"ee57147faa03c1b6864fb013f728e579","index":{"url":"z_c22ab56dc5cc35f0_file_py.html","file":"filterweb/input/file.py","description":"","nums":{"precision":0,"n_files":1,"n_statements":12,"n_excluded":0,"n_missing":0,"n_branches":0,"n_partial_branches":0,"n_missing_branches":0}}},"z_c22ab56dc5cc35f0_grpc_py":{"hash":"58a2bd07cc15623a5374a5c4f58045fb","index":{"url":"z_c22ab56dc5cc35f0_grpc_py.html","file":"filterweb/input/grpc.py","description":"","nums":{"precision":0,"n_files":1,"n_statements":15,"n_excluded":0,"n_missing":12,"n_branches":0,"n_partial_branches":0,"n_missing_branches":0}}},"z_c22ab56dc5cc35f0_http_py":{"hash":"a1777362324d13feeaeb2152249c6fc9","index":{"url":"z_c22ab56dc5cc35f0_http_py.html","file":"filterweb/input/http.py","description":"","nums":{"precision":0,"n_files":1,"n_statements":25,"n_excluded":0,"n_missing":7,"n_branches":2,"n_partial_branches":0,"n_missing_branches":2}}},"z_c22ab56dc5cc35f0_http_unix_py":{"hash":"ffd674d371db3c8d666c62b5fa40615f","index":{"url":"z_c22ab56dc5cc35f0_http_unix_py.html","file":"filterweb/input/http_unix.py","description":"","nums":{"precision":0,"n_files":1,"n_statements":16,"n_excluded":0,"n_missing":4,"n_branches":0,"n_partial_branches":0,"n_missing_branches":0}}},"z_c22ab56dc5cc35f0_input_py":{"hash":"a8a543d6f6e6192c2a668c2ce4954f5c","index":{"url":"z_c22ab56dc5cc35f0_input_py.html","file":"filterweb/input/input.py","description":"","nums":{"precision":0,"n_files":1,"n_statements":74,"n_excluded":0,"n_missing":8,"n_branches":26,"n_partial_branches":2,"n_missing_branches":6}}},"z_c22ab56dc5cc35f0_jsonrpc_py":{"hash":"071dc3efe5ae5d97a63b096022e58436","index":{"url":"z_c22ab56dc5cc35f0_jsonrpc_py.html","file":"filterweb/input/jsonrpc.py","description":"","nums":{"precision":0,"n_files":1,"n_statements":13,"n_excluded":0,"n_missing":2,"n_branches":0,"n_partial_branches":0,"n_missing_branches":0}}},"z_c22ab56dc5cc35f0_process_py":{"hash":"6672a41730b285b012e2f3baddb30688","index":{"url":"z_c22ab56dc5cc35f0_process_py.html","file":"filterweb/input/process.py","description":"","nums":{"precision":0,"n_files":1,"n_statements":14,"n_excluded":0,"n_missing":0,"n_branches":0,"n_partial_branches":0,"n_missing_branches":0}}},"z_c22ab56dc5cc35f0_sftp_py":{"hash":"db168ae004ec59cd4c936b2cf2f0fdcc","index":{"url":"z_c22ab56dc5cc35f0_sftp_py.html","file":"filterweb/input/sftp.py","description":"","nums":{"precision":0,"n_files":1,"n_statements":23,"n_excluded":0,"n_missing":9,"n_branches":0,"n_partial_branches":0,"n_missing_branches":0}}},"z_c22ab56dc5cc35f0_sqlite_py":{"hash":"8e5e4e8154515682e1a1adf1c97df8ce","index":{"url":"z_c22ab56dc5cc35f0_sqlite_py.html","file":"filterweb/input/sqlite.py","description":"","nums":{"precision":0,"n_files":1,"n_statements":28,"n_excluded":0,"n_missing":3,"n_branches":2,"n_partial_branches":1,"n_missing_branches":1}}},"z_c22ab56dc5cc35f0_ssh_py":{"hash":"de1df99dee26892951aa9d86d92fefa4","index":{"url":"z_c22ab56dc5cc35f0_ssh_py.html","file":"filterweb/input/ssh.py","description":"","nums":{"precision":0,"n_files":1,"n_statements":38,"n_excluded":0,"n_missing":0,"n_branches":6,"n_partial_branches":3,"n_missing_branches":3}}},"z_c22ab56dc5cc35f0_xmlrpc_py":{"hash":"8600300f3ca264ba33d284163561fdf2","index":{"url":"z_c22ab56dc5cc35f0_xmlrpc_py.html","file":"filterweb/input/xmlrpc.py","description":"","nums":{"precision":0,"n_files":1,"n_statements":19,"n_excluded":0,"n_missing":0,"n_branches":2,"n_partial_branches":0,"n_missing_branches":0}}},"z_3342f9396610c12e___init___py":{"hash":"fff65cb976bc1980e3bc5cede320ef3f","index":{"url":"z_3342f9396610c12e___init___py.html","file":"filterweb/serve/__init__.py","description":"","nums":{"precision":0,"n_files":1,"n_statements":6,"n_excluded":0,"n_missing":2,"n_branches":0,"n_partial_branches":0,"n_missing_branches":0}}},"z_3342f9396610c12e_flask_py":{"hash":"7e2e84783a45426129bc31068abb963a","index":{"url":"z_3342f9396610c12e_flask_py.html","file":"filterweb/serve/flask.py","description":"","nums":{"precision":0,"n_files":1,"n_statements":63,"n_excluded":0,"n_missing":8,"n_branches":14,"n_partial_branches":2,"n_missing_branches":6}}},"z_3342f9396610c12e_http_py":{"hash":"67de8df09405234a4801b75be36a7fce","index":{"url":"z_3342f9396610c12e_http_py.html","file":"filterweb/serve/http.py","description":"","nums":{"precision":0,"n_files":1,"n_statements":66,"n_excluded":0,"n_missing":6,"n_branches":12,"n_partial_branches":5,"n_missing_branches":5}}},"z_3342f9396610c12e_serve_py":{"hash":"44c604c0c0529e9f459fcfc72819e091","index":{"url":"z_3342f9396610c12e_serve_py.html","file":"filterweb/serve/serve.py","description":"","nums":{"precision":0,"n_files":1,"n_statements":56,"n_excluded":0,"n_missing":3,"n_branches":14,"n_partial_branches":2,"n_missing_branches":2}}},"z_48a8711fda13fe93_trace_py":{"hash":"dc7b0e5d54ba7a778c7930bf114b82a4","index":{"url":"z_48a8711fda13fe93_trace_py.html","file":"filterweb/trace.py","description":"","nums":{"precision":0,"n_files":1,"n_statements":23,"n_excluded":0,"n_missing":4,"n_branches":0,"n_partial_branches":0,"n_missing_branches":0}}}}}